{
  "culture": "zh-Hans",
  "texts": {
    "Menu:EntityUi": "实体 UI",
    "Menu:Module": "模块",
    "Module": "模块",
    "ModuleName": "名称",
    "ModuleLResourceTypeName": "本地化资源类型名",
    "ModuleLResourceTypeAssemblyName": "本地化资源类型Assembly",
    "CreateModule": "新建",
    "EditModule": "编辑",
    "ModuleDeletionConfirmationMessage": "确认删除模块 {0}?",
    "SuccessfullyDeleted": "删除成功",
    "Menu:MenuItem": "菜单项",
    "MenuItem": "菜单项",
    "MenuItemParentName": "父级名称",
    "MenuItemName": "名称",
    "MenuItemModuleName": "模块",
    "MenuItemEntityName": "实体",
    "MenuItemPermission": "要求权限",
    "MenuItemLocalizationItemName": "本地化项名",
    "MenuItemMenuItems": "菜单项",
    "CreateMenuItem": "新建",
    "EditMenuItem": "编辑",
    "MenuItemDeletionConfirmationMessage": "确认删除菜单项 {0}?",
    "Menu:Entity": "实体",
    "Entity": "实体",
    "EntityModuleName": "所属模块",
    "EntityName": "实体",
    "EntityNamespace": "命名空间",
    "EntityBelongsTo": "归属于",
    "EntityKeys": "主键",
    "EntityCreationEnabled": "允许创建",
    "EntityCreationPermission": "创建权限",
    "EntityEditEnabled": "允许编辑",
    "EntityEditPermission": "编辑权限",
    "EntityDeletionEnabled": "允许删除",
    "EntityDeletionPermission": "删除权限",
    "EntityDetailEnabled": "允许详情",
    "EntityDetailPermission": "详情权限",
    "EntityContractsAssemblyName": "应用合约层Assembly",
    "EntityListItemDtoTypeName": "列表项DTO类型名",
    "EntityDetailDtoTypeName": "详情项DTO类型名",
    "EntityCreationDtoTypeName": "新建DTO类型名",
    "EntityEditDtoTypeName": "编辑DTO类型名",
    "EntityGetListInputDtoTypeName": "拉取列表入参DTO类型名",
    "EntityKeyClassTypeName": "主键类类型名",
    "EntityAppServiceInterfaceName": "应用服务接口名",
    "EntityAppServiceGetListMethodName": "应用服务GetList方法名",
    "EntityAppServiceGetMethodName": "应用服务Get方法名",
    "EntityAppServiceCreateMethodName": "应用服务Create方法名",
    "EntityAppServiceUpdateMethodName": "应用服务Update方法名",
    "EntityAppServiceDeleteMethodName": "应用服务Delete方法名",
    "EntityProperties": "属性",
    "CreateEntity": "新建",
    "EditEntity": "编辑",
    "EntityDeletionConfirmationMessage": "确认删除实体 {0}?",
    "Property": "属性",
    "PropertyEntityModuleName": "模块名",
    "PropertyEntityName": "实体",
    "PropertyName": "名称",
    "PropertyIsEntityCollection": "是否为实体集合",
    "PropertyTypeOrEntityName": "类型或实体名",
    "PropertyNullable": "是否可空",
    "PropertyShowIn": "显示于",
    "PropertyShowInList": "显示于列表",
    "PropertyShowInDetail": "显示于详情",
    "PropertyShowInCreation": "显示于新建",
    "PropertyShowInEdit": "显示于编辑",
    "CreateProperty": "新建",
    "EditProperty": "编辑",
    "PropertyDeletionConfirmationMessage": "确认删除属性 {0}?"
  }
}